genisum/__init__.py
genisum-0.1.0.dist-info/LICENSE
genisum-0.1.0.dist-info/METADATA
genisum-0.1.0.dist-info/WHEEL
genisum-0.1.0.dist-info/top_level.txt
genisum-0.1.0.dist-info/RECORD
