Metadata-Version: 2.1
Name: genisum
Version: 0.1.0
Summary: A simple library for summation of a given list
Author: Arefin Genius
License: MIT
License-File: LICENSE
